fast_graphrag/__init__.py
fast_graphrag/_exceptions.py
fast_graphrag/_graphrag.py
fast_graphrag/_llm/__init__.py
fast_graphrag/_llm/_base.py
fast_graphrag/_llm/_default.py
fast_graphrag/_llm/_llm_genai.py
fast_graphrag/_llm/_llm_openai.py
fast_graphrag/_llm/_llm_voyage.py
fast_graphrag/_models.py
fast_graphrag/_policies/__init__.py
fast_graphrag/_policies/_base.py
fast_graphrag/_policies/_graph_upsert.py
fast_graphrag/_policies/_ranking.py
fast_graphrag/_prompt.py
fast_graphrag/_services/__init__.py
fast_graphrag/_services/_base.py
fast_graphrag/_services/_chunk_extraction.py
fast_graphrag/_services/_information_extraction.py
fast_graphrag/_services/_state_manager.py
fast_graphrag/_storage/__init__.py
fast_graphrag/_storage/_base.py
fast_graphrag/_storage/_blob_pickle.py
fast_graphrag/_storage/_default.py
fast_graphrag/_storage/_gdb_igraph.py
fast_graphrag/_storage/_ikv_pickle.py
fast_graphrag/_storage/_namespace.py
fast_graphrag/_storage/_vdb_hnswlib.py
fast_graphrag/_types.py
fast_graphrag/_utils.py
fast_graphrag-0.0.5.dist-info/LICENSE
fast_graphrag-0.0.5.dist-info/METADATA
fast_graphrag-0.0.5.dist-info/WHEEL
fast_graphrag-0.0.5.dist-info/RECORD
