Metadata-Version: 2.1
Name: fast-graphrag
Version: 0.0.5
Summary: 
Author: Luca Pinchetti
Author-email: luca@circlemind.co
Requires-Python: >=3.10,<3.13
Classifier: Programming Language :: Python :: 3
Classifier: Programming Language :: Python :: 3.10
Classifier: Programming Language :: Python :: 3.11
Classifier: Programming Language :: Python :: 3.12
Requires-Dist: aiolimiter (>=1.1.0,<2.0.0)
Requires-Dist: google-genai (>=1.3.0,<2.0.0)
Requires-Dist: hnswlib (>=0.8.0,<0.9.0)
Requires-Dist: igraph (>=0.11.6,<0.12.0)
Requires-Dist: instructor (>=1.6.3,<2.0.0)
Requires-Dist: json-repair (>=0.39.1,<0.40.0)
Requires-Dist: openai (>=1.52.1,<2.0.0)
Requires-Dist: pydantic (>=2.9.2,<3.0.0)
Requires-Dist: python-dotenv (>=1.0.1,<2.0.0)
Requires-Dist: requests (>=2.32.3,<3.0.0)
Requires-Dist: scikit-learn (>=1.5.2,<2.0.0)
Requires-Dist: scipy (>=1.14.1,<2.0.0)
Requires-Dist: scipy-stubs (>=1.14.1.5,<2.0.0.0)
Requires-Dist: sentencepiece (>=0.2.0,<0.3.0)
Requires-Dist: tenacity (>=9.0.0,<10.0.0)
Requires-Dist: tiktoken (>=0.8.0,<0.9.0)
Requires-Dist: vertexai (>=1.71.1,<2.0.0)
Requires-Dist: voyageai (>=0.3.2,<0.4.0)
Requires-Dist: xxhash (>=3.5.0,<4.0.0)
